torchint/__init__.py
torchint/integrate.py
torchint-0.1.2.dist-info/LICENSE
torchint-0.1.2.dist-info/METADATA
torchint-0.1.2.dist-info/WHEEL
torchint-0.1.2.dist-info/top_level.txt
torchint-0.1.2.dist-info/RECORD
