Metadata-Version: 2.2
Name: torchint
Version: 0.1.2
Summary: A PyTorch-based numerical integration library
Home-page: https://github.com/ze-ouyang/torchint
Author: Ze Ouyang
Author-email: ze_ouyang@utexas.edu
Classifier: Programming Language :: Python :: 3
Classifier: License :: OSI Approved :: MIT License
Classifier: Operating System :: OS Independent
Requires-Python: >=3.6
License-File: LICENSE
Dynamic: author
Dynamic: author-email
Dynamic: classifier
Dynamic: description
Dynamic: description-content-type
Dynamic: home-page
Dynamic: requires-python
Dynamic: summary
